LICENSE
MANIFEST.in
README.rst
setup.cfg
setup.py
./__init__.py
./test.py
microsofttranslator.egg-info/PKG-INFO
microsofttranslator.egg-info/SOURCES.txt
microsofttranslator.egg-info/dependency_links.txt
microsofttranslator.egg-info/requires.txt
microsofttranslator.egg-info/top_level.txt