Metadata-Version: 1.1
Name: microsofttranslator
Version: 0.6
Summary: Microsoft Translator V2 - Python API
Home-page: http://openlabs.co.in/
Author: Openlabs Technologies & Consulting (P) Limited
Author-email: info@openlabs.co.in
License: BSD
Keywords: translation microsoft
Platform: UNKNOWN
Classifier: Development Status :: 5 - Production/Stable
Classifier: Intended Audience :: Developers
Classifier: License :: OSI Approved :: BSD License
Classifier: Natural Language :: English
Classifier: Operating System :: OS Independent
Classifier: Topic :: Software Development :: Internationalization
Classifier: Topic :: Utilities
Classifier: Programming Language :: Python :: 3
Classifier: Programming Language :: Python :: 2
